[
    {
        "word": "apple",
        "hint": "A red or green fruit"
    },
    {
        "word": "banana",
        "hint": "A long yellow fruit"
    },
    {
        "word": "grape",
        "hint": "A small purple or green fruit"
    },
    {
        "word": "orange",
        "hint": "A round citrus fruit"
    },
    {
        "word": "pear",
        "hint": "A green fruit with a bell shape"
    },
    {
        "word": "peach",
        "hint": "A soft fruit with fuzzy skin"
    },
    {
        "word": "lemon",
        "hint": "A sour yellow fruit"
    },
    {
        "word": "lime",
        "hint": "A small green citrus fruit"
    }
]
